README.md
althaia/monkey.py
althaia/__init__.py
althaia/marshmallow/orderedset.py
althaia/marshmallow/utils.py
althaia/marshmallow/validate.py
althaia/marshmallow/base.py
althaia/marshmallow/validate.cpython-311-x86_64-linux-musl.so
althaia/marshmallow/fields.cpython-311-x86_64-linux-musl.so
althaia/marshmallow/exceptions.py
althaia/marshmallow/error_store.cpython-311-x86_64-linux-musl.so
althaia/marshmallow/types.py
althaia/marshmallow/types.cpython-311-x86_64-linux-musl.so
althaia/marshmallow/decorators.cpython-311-x86_64-linux-musl.so
althaia/marshmallow/utils.cpython-311-x86_64-linux-musl.so
althaia/marshmallow/warnings.cpython-311-x86_64-linux-musl.so
althaia/marshmallow/decorators.py
althaia/marshmallow/fields.py
althaia/marshmallow/class_registry.py
althaia/marshmallow/schema.py
althaia/marshmallow/orderedset.cpython-311-x86_64-linux-musl.so
althaia/marshmallow/base.cpython-311-x86_64-linux-musl.so
althaia/marshmallow/warnings.py
althaia/marshmallow/error_store.py
althaia/marshmallow/exceptions.cpython-311-x86_64-linux-musl.so
althaia/marshmallow/__init__.py
althaia/marshmallow/class_registry.cpython-311-x86_64-linux-musl.so
althaia/marshmallow/__init__.cpython-311-x86_64-linux-musl.so
althaia/marshmallow/schema.cpython-311-x86_64-linux-musl.so
althaia-3.21.1.dist-info/RECORD
althaia-3.21.1.dist-info/METADATA
althaia-3.21.1.dist-info/WHEEL
