Metadata-Version: 2.1
Name: althaia
Version: 3.21.1
Summary: Marshmallow fork optimized for dumping speed.
Home-page: https://dsimidzija.github.io
License: MIT
Keywords: serialization,rest,json,api,marshal,marshalling,deserialization,validation,schema
Author: Dusko Simidzija
Author-email: dusko.simidzija@gmail.com
Maintainer: Dusko Simidzija
Maintainer-email: dusko.simidzija@gmail.com
Requires-Python: >=3.9,<4.0
Classifier: Development Status :: 5 - Production/Stable
Classifier: Intended Audience :: Developers
Classifier: License :: OSI Approved :: MIT License
Classifier: Programming Language :: Python :: 3
Classifier: Programming Language :: Python :: 3.9
Classifier: Programming Language :: Python :: 3.10
Classifier: Programming Language :: Python :: 3.11
Classifier: Programming Language :: Python :: 3.12
Requires-Dist: packaging (>=17.0)
Project-URL: Repository, https://github.com/dsimidzija/python-althaia
